{
  "minecraft:recipes/decorations/torch": {
    "criteria": {
      "has_stone_pickaxe": "2024-01-03 21:59:24 +0100"
    },
    "done": true
  },
  "minecraft:recipes/building_blocks/smooth_basalt": {
    "criteria": {
      "has_basalt": "2024-01-03 21:59:24 +0100"
    },
    "done": true
  },
  "minecraft:recipes/misc/iron_nugget_from_smelting": {
    "criteria": {
      "has_iron_pickaxe": "2024-01-03 22:04:37 +0100"
    },
    "done": true
  },
  "minecraft:story/iron_tools": {
    "criteria": {
      "iron_pickaxe": "2024-01-03 22:04:37 +0100"
    },
    "done": true
  },
  "minecraft:nether/explore_nether": {
    "criteria": {
      "minecraft:nether_wastes": "2024-01-03 22:01:42 +0100",
      "minecraft:basalt_deltas": "2024-01-03 21:59:25 +0100",
      "minecraft:warped_forest": "2024-01-03 22:01:43 +0100"
    },
    "done": false
  },
  "minecraft:recipes/misc/gold_nugget_from_smelting": {
    "criteria": {
      "has_golden_pickaxe": "2024-01-03 21:59:24 +0100"
    },
    "done": true
  },
  "minecraft:nether/root": {
    "criteria": {
      "entered_nether": "2024-01-03 22:03:22 +0100"
    },
    "done": true
  },
  "minecraft:recipes/decorations/campfire": {
    "criteria": {
      "has_coal": "2024-01-03 21:59:24 +0100"
    },
    "done": true
  },
  "minecraft:story/enter_the_nether": {
    "criteria": {
      "entered_nether": "2024-01-03 22:03:22 +0100"
    },
    "done": true
  },
  "minecraft:story/upgrade_tools": {
    "criteria": {
      "stone_pickaxe": "2024-01-03 21:59:24 +0100"
    },
    "done": true
  },
  "minecraft:recipes/misc/gold_nugget_from_blasting": {
    "criteria": {
      "has_golden_pickaxe": "2024-01-03 21:59:24 +0100"
    },
    "done": true
  },
  "minecraft:adventure/shoot_arrow": {
    "criteria": {
      "shot_arrow": "2024-01-03 22:02:38 +0100"
    },
    "done": true
  },
  "minecraft:recipes/decorations/crafting_table": {
    "criteria": {
      "unlock_right_away": "2024-01-03 21:59:24 +0100"
    },
    "done": true
  },
  "minecraft:recipes/decorations/chest": {
    "criteria": {
      "has_lots_of_items": "2024-01-03 21:59:24 +0100"
    },
    "done": true
  },
  "minecraft:recipes/redstone/dispenser": {
    "criteria": {
      "has_bow": "2024-01-03 21:59:24 +0100"
    },
    "done": true
  },
  "minecraft:adventure/root": {
    "criteria": {
      "killed_something": "2024-01-03 22:02:46 +0100"
    },
    "done": true
  },
  "minecraft:recipes/building_blocks/polished_basalt_from_basalt_stonecutting": {
    "criteria": {
      "has_basalt": "2024-01-03 21:59:24 +0100"
    },
    "done": true
  },
  "minecraft:adventure/kill_all_mobs": {
    "criteria": {
      "minecraft:ghast": "2024-01-03 22:02:46 +0100"
    },
    "done": false
  },
  "minecraft:recipes/misc/iron_nugget_from_blasting": {
    "criteria": {
      "has_iron_pickaxe": "2024-01-03 22:04:37 +0100"
    },
    "done": true
  },
  "minecraft:adventure/kill_a_mob": {
    "criteria": {
      "minecraft:ghast": "2024-01-03 22:02:46 +0100"
    },
    "done": true
  },
  "minecraft:adventure/adventuring_time": {
    "criteria": {
      "minecraft:plains": "2024-01-03 22:03:15 +0100"
    },
    "done": false
  },
  "minecraft:recipes/misc/nether_brick": {
    "criteria": {
      "has_netherrack": "2024-01-03 21:59:24 +0100"
    },
    "done": true
  },
  "minecraft:recipes/building_blocks/coal_block": {
    "criteria": {
      "has_coal": "2024-01-03 21:59:24 +0100"
    },
    "done": true
  },
  "minecraft:recipes/building_blocks/polished_basalt": {
    "criteria": {
      "has_basalt": "2024-01-03 21:59:24 +0100"
    },
    "done": true
  },
  "DataVersion": 3465
}